README.md
setup.cfg
setup.py
src/cli/__init__.py
src/cli/formatters.py
src/cli/main.py
src/cli/structures.py
src/cli/utils.py
src/cli/version_detectors.py
src/cli/vulnerability_index.py
src/cli/vulnerablity_detectors.py
src/ismyk8ssecure.egg-info/PKG-INFO
src/ismyk8ssecure.egg-info/SOURCES.txt
src/ismyk8ssecure.egg-info/dependency_links.txt
src/ismyk8ssecure.egg-info/entry_points.txt
src/ismyk8ssecure.egg-info/requires.txt
src/ismyk8ssecure.egg-info/top_level.txt