Metadata-Version: 2.1
Name: ismyk8ssecure
Version: 0.0.1
Summary: Checks for vulnerabilities in a running k8s cluster
Home-page: https://github.com/ismyk8ssecure/ismyk8ssecure
Author: Shivam Sandbhor
License: UNKNOWN
Project-URL: Bug Tracker, https://github.com/ismyk8ssecure/ismyk8ssecure/issues
Platform: UNKNOWN
Classifier: Programming Language :: Python :: 3
Classifier: Operating System :: OS Independent
Classifier: Intended Audience :: Developers
Classifier: Topic :: Security
Classifier: Topic :: Utilities
Requires-Python: >=3.6
